flask_docs_api/__init__.py
flask_docs_api/api.py
Flask_Docs_Api-1.1.1.2.dist-info/METADATA
Flask_Docs_Api-1.1.1.2.dist-info/WHEEL
Flask_Docs_Api-1.1.1.2.dist-info/top_level.txt
Flask_Docs_Api-1.1.1.2.dist-info/RECORD
