Metadata-Version: 2.1
Name: Flask-Docs-Api
Version: 1.1.1.2
Summary: Easy Docs for flask
Home-page: http://github.com/lwerner-lshigh/flask-api/
Author: Lukas Werner
Author-email: lwerner@lshigh.org
License: MIT
Platform: any
Classifier: Environment :: Web Environment
Classifier: Intended Audience :: Developers
Classifier: License :: OSI Approved :: BSD License
Classifier: Operating System :: OS Independent
Classifier: Programming Language :: Python
Classifier: Topic :: Internet :: WWW/HTTP :: Dynamic Content
Classifier: Topic :: Software Development :: Libraries :: Python Modules
Requires-Dist: Flask
